{
  "11001": [
    {
      "date": "2022-01-01",
      "dataset_name": "counties",
      "region_id": "11001",
      "region_name": "District of Columbia, District of Columbia",
      "ntl_sum": 118579.47095012663,
      "area_km2": 176.92983408270678,
      "light_density": 670.2061953819278,
      "density_3m_smooth": 670.2061953819278,
      "lag_1": null,
      "lag_12": null,
      "mom_pct_display": null,
      "yoy_pct_display": null,
      "mom_capped": false,
      "yoy_capped": false,
      "mom_pct_rank": null,
      "yoy_pct_rank": null,
      "mom_3m_avg": null,
      "vol_12m": null,
      "months_seen": 1,
      "mom_pct_rank_z": null,
      "yoy_pct_rank_z": null,
      "mom_3m_avg_z": null,
      "trend_score": 0.0,
      "trend_label": "Stable",
      "statefp": "11"
    },
    {
      "date": "2022-02-01",
      "dataset_name": "counties",
      "region_id": "11001",
      "region_name": "District of Columbia, District of Columbia",
      "ntl_sum": 97125.1758594513,
      "area_km2": 176.92983408270678,
      "light_density": 548.9474195406165,
      "density_3m_smooth": 609.5768074612722,
      "lag_1": 670.2061953819278,
      "lag_12": null,
      "mom_pct_display": -0.0904637831437905,
      "yoy_pct_display": null,
      "mom_capped": false,
      "yoy_capped": false,
      "mom_pct_rank": -0.0904637831437905,
      "yoy_pct_rank": null,
      "mom_3m_avg": -0.0904637831437905,
      "vol_12m": null,
      "months_seen": 2,
      "mom_pct_rank_z": -0.6044903689964811,
      "yoy_pct_rank_z": null,
      "mom_3m_avg_z": -0.869415856139124,
      "trend_score": -0.3552302819267691,
      "trend_label": "Stable",
      "statefp": "11"
    },
    {
      "date": "2022-03-01",
      "dataset_name": "counties",
      "region_id": "11001",
      "region_name": "District of Columbia, District of Columbia",
      "ntl_sum": 100680.90400266647,
      "area_km2": 176.92983408270678,
      "light_density": 569.0442458426918,
      "density_3m_smooth": 596.0659535884121,
      "lag_1": 609.5768074612722,
      "lag_12": null,
      "mom_pct_display": -0.0221643174534958,
      "yoy_pct_display": null,
      "mom_capped": false,
      "yoy_capped": false,
      "mom_pct_rank": -0.0221643174534958,
      "yoy_pct_rank": null,
      "mom_3m_avg": -0.0563140502986431,
      "vol_12m": null,
      "months_seen": 3,
      "mom_pct_rank_z": -0.2101074987450934,
      "yoy_pct_rank_z": null,
      "mom_3m_avg_z": -0.5802665767255493,
      "trend_score": -0.1790855649686379,
      "trend_label": "Stable",
      "statefp": "11"
    },
    {
      "date": "2022-04-01",
      "dataset_name": "counties",
      "region_id": "11001",
      "region_name": "District of Columbia, District of Columbia",
      "ntl_sum": 90515.20997858047,
      "area_km2": 176.92983408270678,
      "light_density": 511.5881696710837,
      "density_3m_smooth": 543.1932783514641,
      "lag_1": 596.0659535884121,
      "lag_12": null,
      "mom_pct_display": -0.0887027264661671,
      "yoy_pct_display": null,
      "mom_capped": false,
      "yoy_capped": false,
      "mom_pct_rank": -0.0887027264661671,
      "yoy_pct_rank": null,
      "mom_3m_avg": -0.0671102756878178,
      "vol_12m": null,
      "months_seen": 4,
      "mom_pct_rank_z": -0.594321466792387,
      "yoy_pct_rank_z": null,
      "mom_3m_avg_z": -0.6716793208843952,
      "trend_score": -0.3126323042145951,
      "trend_label": "Stable",
      "statefp": "11"
    },
    {
      "date": "2022-05-01",
      "dataset_name": "counties",
      "region_id": "11001",
      "region_name": "District of Columbia, District of Columbia",
      "ntl_sum": 90024.76595783234,
      "area_km2": 176.92983408270678,
      "light_density": 508.816200640022,
      "density_3m_smooth": 529.8162053845991,
      "lag_1": 543.1932783514641,
      "lag_12": null,
      "mom_pct_display": -0.0246267277228889,
      "yoy_pct_display": null,
      "mom_capped": false,
      "yoy_capped": false,
      "mom_pct_rank": -0.0246267277228889,
      "yoy_pct_rank": null,
      "mom_3m_avg": -0.0451645905475173,
      "vol_12m": null,
      "months_seen": 5,
      "mom_pct_rank_z": -0.2243262399894742,
      "yoy_pct_rank_z": null,
      "mom_3m_avg_z": -0.4858629611099499,
      "trend_score": -0.1644704642188322,
      "trend_label": "Stable",
      "statefp": "11"
    },
    {
      "date": "2022-06-01",
      "dataset_name": "counties",
      "region_id": "11001",
      "region_name": "District of Columbia, District of Columbia",
      "ntl_sum": 90477.04256105424,
      "area_km2": 176.92983408270678,
      "light_density": 511.3724490283547,
      "density_3m_smooth": 510.5922731131535,
      "lag_1": 529.8162053845991,
      "lag_12": null,
      "mom_pct_display": -0.0362841530252756,
      "yoy_pct_display": null,
      "mom_capped": false,
      "yoy_capped": false,
      "mom_pct_rank": -0.0362841530252756,
      "yoy_pct_rank": null,
      "mom_3m_avg": -0.0498712024047772,
      "vol_12m": null,
      "months_seen": 6,
      "mom_pct_rank_z": -0.291639926912646,
      "yoy_pct_rank_z": null,
      "mom_3m_avg_z": -0.5257143249017894,
      "trend_score": -0.1926348430541516,
      "trend_label": "Stable",
      "statefp": "11"
    },
    {
      "date": "2022-07-01",
      "dataset_name": "counties",
      "region_id": "11001",
      "region_name": "District of Columbia, District of Columbia",
      "ntl_sum": 91704.51978206636,
      "area_km2": 176.92983408270678,
      "light_density": 518.3100987886452,
      "density_3m_smooth": 512.8329161523405,
      "lag_1": 510.5922731131535,
      "lag_12": null,
      "mom_pct_display": 0.0043883214791433,
      "yoy_pct_display": null,
      "mom_capped": false,
      "yoy_capped": false,
      "mom_pct_rank": 0.0043883214791433,
      "yoy_pct_rank": null,
      "mom_3m_avg": -0.0188408530896737,
      "vol_12m": 0.0384811765639087,
      "months_seen": 7,
      "mom_pct_rank_z": -0.0567841037644056,
      "yoy_pct_rank_z": null,
      "mom_3m_avg_z": -0.2629771847578465,
      "trend_score": -0.069630668080891,
      "trend_label": "Stable",
      "statefp": "11"
    },
    {
      "date": "2022-08-01",
      "dataset_name": "counties",
      "region_id": "11001",
      "region_name": "District of Columbia, District of Columbia",
      "ntl_sum": 89400.444065094,
      "area_km2": 176.92983408270678,
      "light_density": 505.2875594926704,
      "density_3m_smooth": 511.6567024365568,
      "lag_1": 512.8329161523405,
      "lag_12": null,
      "mom_pct_display": -0.0022935612725653,
      "yoy_pct_display": null,
      "mom_capped": false,
      "yoy_capped": false,
      "mom_pct_rank": -0.0022935612725653,
      "yoy_pct_rank": null,
      "mom_3m_avg": -0.0113964642728992,
      "vol_12m": 0.0383462252150638,
      "months_seen": 8,
      "mom_pct_rank_z": -0.0953674231457255,
      "yoy_pct_rank_z": null,
      "mom_3m_avg_z": -0.1999447835438878,
      "trend_score": -0.0685991836524952,
      "trend_label": "Stable",
      "statefp": "11"
    },
    {
      "date": "2022-09-01",
      "dataset_name": "counties",
      "region_id": "11001",
      "region_name": "District of Columbia, District of Columbia",
      "ntl_sum": 85742.023375988,
      "area_km2": 176.92983408270678,
      "light_density": 484.6103192291892,
      "density_3m_smooth": 502.7359925035016,
      "lag_1": 511.6567024365568,
      "lag_12": null,
      "mom_pct_display": -0.0174349517764039,
      "yoy_pct_display": null,
      "mom_capped": false,
      "yoy_capped": false,
      "mom_pct_rank": -0.0174349517764039,
      "yoy_pct_rank": null,
      "mom_3m_avg": -0.0051133971899419,
      "vol_12m": 0.0361804478860204,
      "months_seen": 9,
      "mom_pct_rank_z": -0.1827986348857829,
      "yoy_pct_rank_z": null,
      "mom_3m_avg_z": -0.1467454121818246,
      "trend_score": -0.0841886729020998,
      "trend_label": "Stable",
      "statefp": "11"
    },
    {
      "date": "2022-10-01",
      "dataset_name": "counties",
      "region_id": "11001",
      "region_name": "District of Columbia, District of Columbia",
      "ntl_sum": 84816.8257522583,
      "area_km2": 176.92983408270678,
      "light_density": 479.3811410720604,
      "density_3m_smooth": 489.75967326464,
      "lag_1": 502.7359925035016,
      "lag_12": null,
      "mom_pct_display": -0.0258113988899873,
      "yoy_pct_display": null,
      "mom_capped": false,
      "yoy_capped": false,
      "mom_pct_rank": -0.0258113988899873,
      "yoy_pct_rank": null,
      "mom_3m_avg": -0.0151799706463188,
      "vol_12m": 0.0339730896531485,
      "months_seen": 10,
      "mom_pct_rank_z": -0.2311669086603375,
      "yoy_pct_rank_z": null,
      "mom_3m_avg_z": -0.2319801188272329,
      "trend_score": -0.1157460963635478,
      "trend_label": "Stable",
      "statefp": "11"
    },
    {
      "date": "2022-11-01",
      "dataset_name": "counties",
      "region_id": "11001",
      "region_name": "District of Columbia, District of Columbia",
      "ntl_sum": 91058.8408346176,
      "area_km2": 176.92983408270678,
      "light_density": 514.6607484640023,
      "density_3m_smooth": 492.8840695884173,
      "lag_1": 489.75967326464,
      "lag_12": null,
      "mom_pct_display": 0.0063794479095241,
      "yoy_pct_display": null,
      "mom_capped": false,
      "yoy_capped": false,
      "mom_pct_rank": 0.0063794479095241,
      "yoy_pct_rank": null,
      "mom_3m_avg": -0.0122889675856223,
      "vol_12m": 0.0344477711910289,
      "months_seen": 11,
      "mom_pct_rank_z": -0.0452867055240188,
      "yoy_pct_rank_z": null,
      "mom_3m_avg_z": -0.2075017003408167,
      "trend_score": -0.055086351725369,
      "trend_label": "Stable",
      "statefp": "11"
    },
    {
      "date": "2022-12-01",
      "dataset_name": "counties",
      "region_id": "11001",
      "region_name": "District of Columbia, District of Columbia",
      "ntl_sum": 98981.9830493927,
      "area_km2": 176.92983408270678,
      "light_density": 559.4420158848002,
      "density_3m_smooth": 517.8279684736209,
      "lag_1": 492.8840695884173,
      "lag_12": null,
      "mom_pct_display": 0.0506080444150547,
      "yoy_pct_display": null,
      "mom_capped": false,
      "yoy_capped": false,
      "mom_pct_rank": 0.0506080444150547,
      "yoy_pct_rank": null,
      "mom_3m_avg": 0.0103920311448638,
      "vol_12m": 0.0406732310506291,
      "months_seen": 12,
      "mom_pct_rank_z": 0.2101032987863707,
      "yoy_pct_rank_z": null,
      "mom_3m_avg_z": -0.0154593652209913,
      "trend_score": 0.0599391165917129,
      "trend_label": "Stable",
      "statefp": "11"
    },
    {
      "date": "2023-01-01",
      "dataset_name": "counties",
      "region_id": "11001",
      "region_name": "District of Columbia, District of Columbia",
      "ntl_sum": 94719.21652078629,
      "area_km2": 176.92983408270678,
      "light_density": 535.3490382888693,
      "density_3m_smooth": 536.4839342125573,
      "lag_1": 517.8279684736209,
      "lag_12": 670.2061953819278,
      "mom_pct_display": 0.036027342814116,
      "yoy_pct_display": -0.1995240600441879,
      "mom_capped": false,
      "yoy_capped": false,
      "mom_pct_rank": 0.036027342814116,
      "yoy_pct_rank": -0.1995240600441879,
      "mom_3m_avg": 0.0310049450462316,
      "vol_12m": 0.0422895308717362,
      "months_seen": 13,
      "mom_pct_rank_z": 0.1259096833672921,
      "yoy_pct_rank_z": -1.0572472160394093,
      "mom_3m_avg_z": 0.1590722842130243,
      "trend_score": -0.4590362461669121,
      "trend_label": "Stable",
      "statefp": "11"
    },
    {
      "date": "2023-02-01",
      "dataset_name": "counties",
      "region_id": "11001",
      "region_name": "District of Columbia, District of Columbia",
      "ntl_sum": 97779.9120144844,
      "area_km2": 176.92983408270678,
      "light_density": 552.6479608225749,
      "density_3m_smooth": 549.1463383320815,
      "lag_1": 536.4839342125573,
      "lag_12": 609.5768074612722,
      "mom_pct_display": 0.023602578403601,
      "yoy_pct_display": -0.0991351186421736,
      "mom_capped": false,
      "yoy_capped": false,
      "mom_pct_rank": 0.023602578403601,
      "yoy_pct_rank": -0.0991351186421736,
      "mom_3m_avg": 0.0367459885442572,
      "vol_12m": 0.0368795221383339,
      "months_seen": 14,
      "mom_pct_rank_z": 0.0541651360140838,
      "yoy_pct_rank_z": -0.6723516484729984,
      "mom_3m_avg_z": 0.2076822864658528,
      "trend_score": -0.2783898261391035,
      "trend_label": "Stable",
      "statefp": "11"
    },
    {
      "date": "2023-03-01",
      "dataset_name": "counties",
      "region_id": "11001",
      "region_name": "District of Columbia, District of Columbia",
      "ntl_sum": 92747.6595492363,
      "area_km2": 176.92983408270678,
      "light_density": 524.205880992806,
      "density_3m_smooth": 537.40096003475,
      "lag_1": 549.1463383320815,
      "lag_12": 596.0659535884121,
      "mom_pct_display": -0.0213884305101727,
      "yoy_pct_display": -0.0984203060089062,
      "mom_capped": false,
      "yoy_capped": false,
      "mom_pct_rank": -0.0213884305101727,
      "yoy_pct_rank": -0.0984203060089062,
      "mom_3m_avg": 0.0127471635691814,
      "vol_12m": 0.0368531521531036,
      "months_seen": 15,
      "mom_pct_rank_z": -0.205627280391909,
      "yoy_pct_rank_z": -0.6696110257475997,
      "mom_3m_avg_z": 0.0044817818006535,
      "trend_score": -0.3955973406312418,
      "trend_label": "Stable",
      "statefp": "11"
    },
    {
      "date": "2023-04-01",
      "dataset_name": "counties",
      "region_id": "11001",
      "region_name": "District of Columbia, District of Columbia",
      "ntl_sum": 89774.51655006409,
      "area_km2": 176.92983408270678,
      "light_density": 507.4018014853194,
      "density_3m_smooth": 528.0852144335668,
      "lag_1": 537.40096003475,
      "lag_12": 543.1932783514641,
      "mom_pct_display": -0.0173348138428723,
      "yoy_pct_display": -0.0278134220728001,
      "mom_capped": false,
      "yoy_capped": false,
      "mom_pct_rank": -0.0173348138428723,
      "yoy_pct_rank": -0.0278134220728001,
      "mom_3m_avg": -0.0050402219831479,
      "vol_12m": 0.0271091177863979,
      "months_seen": 16,
      "mom_pct_rank_z": -0.1822204065607429,
      "yoy_pct_rank_z": -0.3989011618209147,
      "mom_3m_avg_z": -0.1461258302245847,
      "trend_score": -0.2833418689235971,
      "trend_label": "Stable",
      "statefp": "11"
    },
    {
      "date": "2023-05-01",
      "dataset_name": "counties",
      "region_id": "11001",
      "region_name": "District of Columbia, District of Columbia",
      "ntl_sum": 78868.9209318161,
      "area_km2": 176.92983408270678,
      "light_density": 445.7638325425005,
      "density_3m_smooth": 492.457171673542,
      "lag_1": 528.0852144335668,
      "lag_12": 529.8162053845991,
      "mom_pct_display": -0.0674664652337219,
      "yoy_pct_display": -0.0705131955787155,
      "mom_capped": false,
      "yoy_capped": false,
      "mom_pct_rank": -0.0674664652337219,
      "yoy_pct_rank": -0.0705131955787155,
      "mom_3m_avg": -0.0353965698622556,
      "vol_12m": 0.0326185914731199,
      "months_seen": 17,
      "mom_pct_rank_z": -0.4716965300727117,
      "yoy_pct_rank_z": -0.5626139505901637,
      "mom_3m_avg_z": -0.403156131301129,
      "trend_score": -0.5034471605771211,
      "trend_label": "Weak",
      "statefp": "11"
    },
    {
      "date": "2023-06-01",
      "dataset_name": "counties",
      "region_id": "11001",
      "region_name": "District of Columbia, District of Columbia",
      "ntl_sum": 82280.32989120483,
      "area_km2": 176.92983408270678,
      "light_density": 465.0449728718022,
      "density_3m_smooth": 472.7368689665407,
      "lag_1": 492.457171673542,
      "lag_12": 510.5922731131535,
      "mom_pct_display": -0.0400447061010092,
      "yoy_pct_display": -0.0741401821766768,
      "mom_capped": false,
      "yoy_capped": false,
      "mom_pct_rank": -0.0400447061010092,
      "yoy_pct_rank": -0.0741401821766768,
      "mom_3m_avg": -0.0416153283925344,
      "vol_12m": 0.0329566657226088,
      "months_seen": 18,
      "mom_pct_rank_z": -0.3133545582168734,
      "yoy_pct_rank_z": -0.5765199749558121,
      "mom_3m_avg_z": -0.4558109955728611,
      "trend_score": -0.4734285540575403,
      "trend_label": "Stable",
      "statefp": "11"
    },
    {
      "date": "2023-07-01",
      "dataset_name": "counties",
      "region_id": "11001",
      "region_name": "District of Columbia, District of Columbia",
      "ntl_sum": 79365.32112503052,
      "area_km2": 176.92983408270678,
      "light_density": 448.5694656104792,
      "density_3m_smooth": 453.126090341594,
      "lag_1": 472.7368689665407,
      "lag_12": 512.8329161523405,
      "mom_pct_display": -0.0414834972948445,
      "yoy_pct_display": -0.1164254944060771,
      "mom_capped": false,
      "yoy_capped": false,
      "mom_pct_rank": -0.0414834972948445,
      "yoy_pct_rank": -0.1164254944060771,
      "mom_3m_avg": -0.0496648895431918,
      "vol_12m": 0.0342885931618318,
      "months_seen": 19,
      "mom_pct_rank_z": -0.3216625968666959,
      "yoy_pct_rank_z": -0.738643701164677,
      "mom_3m_avg_z": -0.5239674528096512,
      "trend_score": -0.5706141202042775,
      "trend_label": "Weak",
      "statefp": "11"
    },
    {
      "date": "2023-08-01",
      "dataset_name": "counties",
      "region_id": "11001",
      "region_name": "District of Columbia, District of Columbia",
      "ntl_sum": 77509.8608174324,
      "area_km2": 176.92983408270678,
      "light_density": 438.0824817887978,
      "density_3m_smooth": 450.56564009035975,
      "lag_1": 453.126090341594,
      "lag_12": 511.6567024365568,
      "mom_pct_display": -0.0056506352333497,
      "yoy_pct_display": -0.1193985382293942,
      "mom_capped": false,
      "yoy_capped": false,
      "mom_pct_rank": -0.0056506352333497,
      "yoy_pct_rank": -0.1193985382293942,
      "mom_3m_avg": -0.0290596128764011,
      "vol_12m": 0.0342361480632841,
      "months_seen": 20,
      "mom_pct_rank_z": -0.114752237520466,
      "yoy_pct_rank_z": -0.7500424804903097,
      "mom_3m_avg_z": -0.3495004686216179,
      "trend_score": -0.4793470052256183,
      "trend_label": "Stable",
      "statefp": "11"
    },
    {
      "date": "2023-09-01",
      "dataset_name": "counties",
      "region_id": "11001",
      "region_name": "District of Columbia, District of Columbia",
      "ntl_sum": 82162.85664749146,
      "area_km2": 176.92983408270678,
      "light_density": 464.381019026356,
      "density_3m_smooth": 450.3443221418777,
      "lag_1": 450.56564009035975,
      "lag_12": 502.7359925035016,
      "mom_pct_display": -0.0004912002354144,
      "yoy_pct_display": -0.1042130882667187,
      "mom_capped": false,
      "yoy_capped": false,
      "mom_pct_rank": -0.0004912002354144,
      "yoy_pct_rank": -0.1042130882667187,
      "mom_3m_avg": -0.0158751109212029,
      "vol_12m": 0.0342510246876781,
      "months_seen": 21,
      "mom_pct_rank_z": -0.0849600164130863,
      "yoy_pct_rank_z": -0.6918208048703891,
      "mom_3m_avg_z": -0.2378659426046988,
      "trend_score": -0.4189715958800602,
      "trend_label": "Stable",
      "statefp": "11"
    },
    {
      "date": "2023-10-01",
      "dataset_name": "counties",
      "region_id": "11001",
      "region_name": "District of Columbia, District of Columbia",
      "ntl_sum": 76458.74161148071,
      "area_km2": 176.92983408270678,
      "light_density": 432.1416001313813,
      "density_3m_smooth": 444.8683669821783,
      "lag_1": 450.3443221418777,
      "lag_12": 489.75967326464,
      "mom_pct_display": -0.0121594852881795,
      "yoy_pct_display": -0.0916598665284653,
      "mom_capped": false,
      "yoy_capped": false,
      "mom_pct_rank": -0.0121594852881795,
      "yoy_pct_rank": -0.0916598665284653,
      "mom_3m_avg": -0.0061004402523145,
      "vol_12m": 0.0338513236836346,
      "months_seen": 22,
      "mom_pct_rank_z": -0.1523364109940876,
      "yoy_pct_rank_z": -0.6436912067467941,
      "mom_3m_avg_z": -0.1551028067046275,
      "trend_score": -0.3985670880125488,
      "trend_label": "Stable",
      "statefp": "11"
    },
    {
      "date": "2023-11-01",
      "dataset_name": "counties",
      "region_id": "11001",
      "region_name": "District of Columbia, District of Columbia",
      "ntl_sum": 76570.06345009804,
      "area_km2": 176.92983408270678,
      "light_density": 432.7707864932771,
      "density_3m_smooth": 443.0978018836715,
      "lag_1": 444.8683669821783,
      "lag_12": 492.8840695884173,
      "mom_pct_display": -0.0039799752689041,
      "yoy_pct_display": -0.1010100970524769,
      "mom_capped": false,
      "yoy_capped": false,
      "mom_pct_rank": -0.0039799752689041,
      "yoy_pct_rank": -0.1010100970524769,
      "mom_3m_avg": -0.0055435535974994,
      "vol_12m": 0.0335977196582081,
      "months_seen": 23,
      "mom_pct_rank_z": -0.1051053147322288,
      "yoy_pct_rank_z": -0.679540397246815,
      "mom_3m_avg_z": -0.1503875904631121,
      "trend_score": -0.4013793111356986,
      "trend_label": "Stable",
      "statefp": "11"
    },
    {
      "date": "2023-12-01",
      "dataset_name": "counties",
      "region_id": "11001",
      "region_name": "District of Columbia, District of Columbia",
      "ntl_sum": 76244.74775075912,
      "area_km2": 176.92983408270678,
      "light_density": 430.9321158076604,
      "density_3m_smooth": 431.94816747743965,
      "lag_1": 443.0978018836715,
      "lag_12": 517.8279684736209,
      "mom_pct_display": -0.0251629196959072,
      "yoy_pct_display": -0.1658462003304406,
      "mom_capped": false,
      "yoy_capped": false,
      "mom_pct_rank": -0.0251629196959072,
      "yoy_pct_rank": -0.1658462003304406,
      "mom_3m_avg": -0.0137674600843303,
      "vol_12m": 0.0282047738510549,
      "months_seen": 24,
      "mom_pct_rank_z": -0.2274223832343361,
      "yoy_pct_rank_z": -0.9281248371407648,
      "mom_3m_avg_z": -0.2200202474860698,
      "trend_score": -0.5762931830378971,
      "trend_label": "Weak",
      "statefp": "11"
    },
    {
      "date": "2024-01-01",
      "dataset_name": "counties",
      "region_id": "11001",
      "region_name": "District of Columbia, District of Columbia",
      "ntl_sum": 80800.76342773438,
      "area_km2": 176.92983408270678,
      "light_density": 456.6825252883221,
      "density_3m_smooth": 440.1284758630865,
      "lag_1": 431.94816747743965,
      "lag_12": 536.4839342125573,
      "mom_pct_display": 0.0189381712936057,
      "yoy_pct_display": -0.1796054871445494,
      "mom_capped": false,
      "yoy_capped": false,
      "mom_pct_rank": 0.0189381712936057,
      "yoy_pct_rank": -0.1796054871445494,
      "mom_3m_avg": -0.0034015745570685,
      "vol_12m": 0.0257381927047767,
      "months_seen": 25,
      "mom_pct_rank_z": 0.0272313636123719,
      "yoy_pct_rank_z": -0.980878541220756,
      "mom_3m_avg_z": -0.1322512349352949,
      "trend_score": -0.5087201085137253,
      "trend_label": "Weak",
      "statefp": "11"
    },
    {
      "date": "2024-02-01",
      "dataset_name": "counties",
      "region_id": "11001",
      "region_name": "District of Columbia, District of Columbia",
      "ntl_sum": 89678.80890846252,
      "area_km2": 176.92983408270678,
      "light_density": 506.8608659099386,
      "density_3m_smooth": 464.8251690019737,
      "lag_1": 440.1284758630865,
      "lag_12": 549.1463383320815,
      "mom_pct_display": 0.0561124637310896,
      "yoy_pct_display": -0.1535495430711892,
      "mom_capped": false,
      "yoy_capped": false,
      "mom_pct_rank": 0.0561124637310896,
      "yoy_pct_rank": -0.1535495430711892,
      "mom_3m_avg": 0.0166292384429294,
      "vol_12m": 0.0313834580771109,
      "months_seen": 26,
      "mom_pct_rank_z": 0.2418875692339431,
      "yoy_pct_rank_z": -0.8809789183884603,
      "mom_3m_avg_z": 0.0373517066537631,
      "trend_score": -0.3604528470932946,
      "trend_label": "Stable",
      "statefp": "11"
    },
    {
      "date": "2024-03-01",
      "dataset_name": "counties",
      "region_id": "11001",
      "region_name": "District of Columbia, District of Columbia",
      "ntl_sum": 84442.35210323334,
      "area_km2": 176.92983408270678,
      "light_density": 477.2646317170021,
      "density_3m_smooth": 480.2693409717543,
      "lag_1": 464.8251690019737,
      "lag_12": 537.40096003475,
      "mom_pct_display": 0.0332257652978231,
      "yoy_pct_display": -0.1063109732057446,
      "mom_capped": false,
      "yoy_capped": false,
      "mom_pct_rank": 0.0332257652978231,
      "yoy_pct_rank": -0.1063109732057446,
      "mom_3m_avg": 0.0360921334408395,
      "vol_12m": 0.033964495609523,
      "months_seen": 27,
      "mom_pct_rank_z": 0.1097324824047324,
      "yoy_pct_rank_z": -0.6998641869702343,
      "mom_3m_avg_z": 0.2021460284561213,
      "trend_score": -0.2765831430724731,
      "trend_label": "Stable",
      "statefp": "11"
    },
    {
      "date": "2024-04-01",
      "dataset_name": "counties",
      "region_id": "11001",
      "region_name": "District of Columbia, District of Columbia",
      "ntl_sum": 80241.78239393234,
      "area_km2": 176.92983408270678,
      "light_density": 453.5231879346188,
      "density_3m_smooth": 479.2162285205198,
      "lag_1": 480.2693409717543,
      "lag_12": 528.0852144335668,
      "mom_pct_display": -0.0021927538599563,
      "yoy_pct_display": -0.0925399624480391,
      "mom_capped": false,
      "yoy_capped": false,
      "mom_pct_rank": -0.0021927538599563,
      "yoy_pct_rank": -0.0925399624480391,
      "mom_3m_avg": 0.0290484917229854,
      "vol_12m": 0.0338994545647324,
      "months_seen": 28,
      "mom_pct_rank_z": -0.0947853290352436,
      "yoy_pct_rank_z": -0.6470655327805823,
      "mom_3m_avg_z": 0.1425067939004609,
      "trend_score": -0.3234670063207721,
      "trend_label": "Stable",
      "statefp": "11"
    },
    {
      "date": "2024-05-01",
      "dataset_name": "counties",
      "region_id": "11001",
      "region_name": "District of Columbia, District of Columbia",
      "ntl_sum": 63277.597697258,
      "area_km2": 176.92983408270678,
      "light_density": 357.6423276793362,
      "density_3m_smooth": 429.47671577698566,
      "lag_1": 479.2162285205198,
      "lag_12": 492.457171673542,
      "mom_pct_display": -0.1037934647937414,
      "yoy_pct_display": -0.127890219737336,
      "mom_capped": false,
      "yoy_capped": false,
      "mom_pct_rank": -0.1037934647937414,
      "yoy_pct_rank": -0.127890219737336,
      "mom_3m_avg": -0.0242534844519582,
      "vol_12m": 0.0406819548238066,
      "months_seen": 29,
      "mom_pct_rank_z": -0.6814601967325115,
      "yoy_pct_rank_z": -0.7825999567217193,
      "mom_3m_avg_z": -0.3088064878810263,
      "trend_score": -0.6574993349568184,
      "trend_label": "Weak",
      "statefp": "11"
    },
    {
      "date": "2024-06-01",
      "dataset_name": "counties",
      "region_id": "11001",
      "region_name": "District of Columbia, District of Columbia",
      "ntl_sum": 67812.13187885284,
      "area_km2": 176.92983408270678,
      "light_density": 383.2713246492602,
      "density_3m_smooth": 398.1456134210717,
      "lag_1": 429.47671577698566,
      "lag_12": 472.7368689665407,
      "mom_pct_display": -0.0729518067102461,
      "yoy_pct_display": -0.1577859914089934,
      "mom_capped": false,
      "yoy_capped": false,
      "mom_pct_rank": -0.0729518067102461,
      "yoy_pct_rank": -0.1577859914089934,
      "mom_3m_avg": -0.0596460084546479,
      "vol_12m": 0.0438370877834341,
      "months_seen": 30,
      "mom_pct_rank_z": -0.5033706389981056,
      "yoy_pct_rank_z": -0.8972216455720762,
      "mom_3m_avg_z": -0.6084786070864798,
      "trend_score": -0.7213177359027658,
      "trend_label": "Weak",
      "statefp": "11"
    },
    {
      "date": "2024-07-01",
      "dataset_name": "counties",
      "region_id": "11001",
      "region_name": "District of Columbia, District of Columbia",
      "ntl_sum": 72459.83319282532,
      "area_km2": 176.92983408270678,
      "light_density": 409.5399375040028,
      "density_3m_smooth": 383.4845299441997,
      "lag_1": 398.1456134210717,
      "lag_12": 453.126090341594,
      "mom_pct_display": -0.0368234208356495,
      "yoy_pct_display": -0.1536913496746439,
      "mom_capped": false,
      "yoy_capped": false,
      "mom_pct_rank": -0.0368234208356495,
      "yoy_pct_rank": -0.1536913496746439,
      "mom_3m_avg": -0.0711895641132123,
      "vol_12m": 0.0435846269322653,
      "months_seen": 31,
      "mom_pct_rank_z": -0.2947538310221427,
      "yoy_pct_rank_z": -0.8815226110737215,
      "mom_3m_avg_z": -0.7062190730420925,
      "trend_score": -0.6704312694519221,
      "trend_label": "Weak",
      "statefp": "11"
    },
    {
      "date": "2024-08-01",
      "dataset_name": "counties",
      "region_id": "11001",
      "region_name": "District of Columbia, District of Columbia",
      "ntl_sum": 67338.84578990936,
      "area_km2": 176.92983408270678,
      "light_density": 380.5963315289804,
      "density_3m_smooth": 391.1358645607477,
      "lag_1": 383.4845299441997,
      "lag_12": 450.56564009035975,
      "mom_pct_display": 0.0199521337083958,
      "yoy_pct_display": -0.1319003719806364,
      "mom_capped": false,
      "yoy_capped": false,
      "mom_pct_rank": 0.0199521337083958,
      "yoy_pct_rank": -0.1319003719806364,
      "mom_3m_avg": -0.0299410312791666,
      "vol_12m": 0.0445874550033475,
      "months_seen": 32,
      "mom_pct_rank_z": 0.0330863055717315,
      "yoy_pct_rank_z": -0.7979750548366782,
      "mom_3m_avg_z": -0.3569635283526315,
      "trend_score": -0.4604543414173459,
      "trend_label": "Stable",
      "statefp": "11"
    },
    {
      "date": "2024-09-01",
      "dataset_name": "counties",
      "region_id": "11001",
      "region_name": "District of Columbia, District of Columbia",
      "ntl_sum": 70046.97140359879,
      "area_km2": 176.92983408270678,
      "light_density": 395.9025438912409,
      "density_3m_smooth": 395.3462709747414,
      "lag_1": 391.1358645607477,
      "lag_12": 450.3443221418777,
      "mom_pct_display": 0.0107645623822351,
      "yoy_pct_display": -0.1221244467023824,
      "mom_capped": false,
      "yoy_capped": false,
      "mom_pct_rank": 0.0107645623822351,
      "yoy_pct_rank": -0.1221244467023824,
      "mom_3m_avg": -0.0020355749150061,
      "vol_12m": 0.0449405069427168,
      "months_seen": 33,
      "mom_pct_rank_z": -0.0199656577727705,
      "yoy_pct_rank_z": -0.7604937321340871,
      "mom_3m_avg_z": -0.1206851763083485,
      "trend_score": -0.4103735986605444,
      "trend_label": "Stable",
      "statefp": "11"
    },
    {
      "date": "2024-10-01",
      "dataset_name": "counties",
      "region_id": "11001",
      "region_name": "District of Columbia, District of Columbia",
      "ntl_sum": 69430.49649882317,
      "area_km2": 176.92983408270678,
      "light_density": 392.41825359067207,
      "density_3m_smooth": 389.6390430036311,
      "lag_1": 395.3462709747414,
      "lag_12": 444.8683669821783,
      "mom_pct_display": -0.0144360232791342,
      "yoy_pct_display": -0.1241475638135442,
      "mom_capped": false,
      "yoy_capped": false,
      "mom_pct_rank": -0.0144360232791342,
      "yoy_pct_rank": -0.1241475638135442,
      "mom_3m_avg": 0.0054268909371656,
      "vol_12m": 0.0449559945004135,
      "months_seen": 34,
      "mom_pct_rank_z": -0.1654818664970669,
      "yoy_pct_rank_z": -0.7682504511300134,
      "mom_3m_avg_z": -0.0574997149875144,
      "trend_score": -0.4452697285116297,
      "trend_label": "Stable",
      "statefp": "11"
    },
    {
      "date": "2024-11-01",
      "dataset_name": "counties",
      "region_id": "11001",
      "region_name": "District of Columbia, District of Columbia",
      "ntl_sum": 72857.13656759262,
      "area_km2": 176.92983408270678,
      "light_density": 411.7854795112461,
      "density_3m_smooth": 400.0354256643864,
      "lag_1": 389.6390430036311,
      "lag_12": 443.0978018836715,
      "mom_pct_display": 0.026682086529656,
      "yoy_pct_display": -0.0971848112001929,
      "mom_capped": false,
      "yoy_capped": false,
      "mom_pct_rank": 0.026682086529656,
      "yoy_pct_rank": -0.0971848112001929,
      "mom_3m_avg": 0.0076702085442523,
      "vol_12m": 0.0461856121377865,
      "months_seen": 35,
      "mom_pct_rank_z": 0.0719471968463489,
      "yoy_pct_rank_z": -0.6648740849154342,
      "mom_3m_avg_z": -0.0385053154551303,
      "trend_score": -0.3185539464948385,
      "trend_label": "Stable",
      "statefp": "11"
    },
    {
      "date": "2024-12-01",
      "dataset_name": "counties",
      "region_id": "11001",
      "region_name": "District of Columbia, District of Columbia",
      "ntl_sum": 74203.84196805954,
      "area_km2": 176.92983408270678,
      "light_density": 419.3970019401734,
      "density_3m_smooth": 407.8669116806972,
      "lag_1": 400.0354256643864,
      "lag_12": 431.94816747743965,
      "mom_pct_display": 0.0195769812218609,
      "yoy_pct_display": -0.0557503367530785,
      "mom_capped": false,
      "yoy_capped": false,
      "mom_pct_rank": 0.0195769812218609,
      "yoy_pct_rank": -0.0557503367530785,
      "mom_3m_avg": 0.0106076814907942,
      "vol_12m": 0.0464329922208111,
      "months_seen": 36,
      "mom_pct_rank_z": 0.0309200556175596,
      "yoy_pct_rank_z": -0.5060125077694672,
      "mom_3m_avg_z": -0.0136334316942544,
      "trend_score": -0.2464569235383165,
      "trend_label": "Stable",
      "statefp": "11"
    },
    {
      "date": "2025-01-01",
      "dataset_name": "counties",
      "region_id": "11001",
      "region_name": "District of Columbia, District of Columbia",
      "ntl_sum": 118022.20255374908,
      "area_km2": 176.92983408270678,
      "light_density": 667.0565377831022,
      "density_3m_smooth": 499.4130064115072,
      "lag_1": 407.8669116806972,
      "lag_12": 440.1284758630865,
      "mom_pct_display": 0.224450898342246,
      "yoy_pct_display": 0.1346982388089397,
      "mom_capped": false,
      "yoy_capped": false,
      "mom_pct_rank": 0.224450898342246,
      "yoy_pct_rank": 0.1346982388089397,
      "mom_3m_avg": 0.0902366553645876,
      "vol_12m": 0.0807665831528185,
      "months_seen": 37,
      "mom_pct_rank_z": 1.2139273113399682,
      "yoy_pct_rank_z": 0.2241756141433983,
      "mom_3m_avg_z": 0.6605932312332571,
      "trend_score": 0.6083846467203411,
      "trend_label": "Strong",
      "statefp": "11"
    },
    {
      "date": "2025-02-01",
      "dataset_name": "counties",
      "region_id": "11001",
      "region_name": "District of Columbia, District of Columbia",
      "ntl_sum": 86878.17709541321,
      "area_km2": 176.92983408270678,
      "light_density": 491.0318123895462,
      "density_3m_smooth": 525.8284507042739,
      "lag_1": 499.4130064115072,
      "lag_12": 464.8251690019737,
      "mom_pct_display": 0.0528929842708197,
      "yoy_pct_display": 0.1312391965204473,
      "mom_capped": false,
      "yoy_capped": false,
      "mom_pct_rank": 0.0528929842708197,
      "yoy_pct_rank": 0.1312391965204473,
      "mom_3m_avg": 0.0989736212783089,
      "vol_12m": 0.0806169411441337,
      "months_seen": 38,
      "mom_pct_rank_z": 0.2232972693330018,
      "yoy_pct_rank_z": 0.2109134955646799,
      "mom_3m_avg_z": 0.7345700148780653,
      "trend_score": 0.3193599315578536,
      "trend_label": "Stable",
      "statefp": "11"
    },
    {
      "date": "2025-03-01",
      "dataset_name": "counties",
      "region_id": "11001",
      "region_name": "District of Columbia, District of Columbia",
      "ntl_sum": 86832.90223169327,
      "area_km2": 176.92983408270678,
      "light_density": 490.775920759089,
      "density_3m_smooth": 549.6214236439124,
      "lag_1": 525.8284507042739,
      "lag_12": 480.2693409717543,
      "mom_pct_display": 0.0452485461898669,
      "yoy_pct_display": 0.1444024774345045,
      "mom_capped": false,
      "yoy_capped": false,
      "mom_pct_rank": 0.0452485461898669,
      "yoy_pct_rank": 0.1444024774345045,
      "mom_3m_avg": 0.1075308096009775,
      "vol_12m": 0.0809635966097296,
      "months_seen": 39,
      "mom_pct_rank_z": 0.179155848878909,
      "yoy_pct_rank_z": 0.2613820871017007,
      "mom_3m_avg_z": 0.8070246032792594,
      "trend_score": 0.3458427188703749,
      "trend_label": "Stable",
      "statefp": "11"
    },
    {
      "date": "2025-04-01",
      "dataset_name": "counties",
      "region_id": "11001",
      "region_name": "District of Columbia, District of Columbia",
      "ntl_sum": 82435.12228679657,
      "area_km2": 176.92983408270678,
      "light_density": 465.9198529981204,
      "density_3m_smooth": 482.5758620489185,
      "lag_1": 549.6214236439124,
      "lag_12": 479.2162285205198,
      "mom_pct_display": -0.1219849858662555,
      "yoy_pct_display": 0.0070106839636272,
      "mom_capped": false,
      "yoy_capped": false,
      "mom_pct_rank": -0.1219849858662555,
      "yoy_pct_rank": 0.0070106839636272,
      "mom_3m_avg": -0.0079478184685229,
      "vol_12m": 0.0900340206405816,
      "months_seen": 40,
      "mom_pct_rank_z": -0.7865038339309234,
      "yoy_pct_rank_z": -0.2653840246672534,
      "mom_3m_avg_z": -0.1707447469342385,
      "trend_score": -0.4027921118997514,
      "trend_label": "Stable",
      "statefp": "11"
    },
    {
      "date": "2025-05-01",
      "dataset_name": "counties",
      "region_id": "11001",
      "region_name": "District of Columbia, District of Columbia",
      "ntl_sum": 74483.24292182922,
      "area_km2": 176.92983408270678,
      "light_density": 420.976164409964,
      "density_3m_smooth": 459.2239793890578,
      "lag_1": 482.5758620489185,
      "lag_12": 429.47671577698566,
      "mom_pct_display": -0.0483900760405077,
      "yoy_pct_display": 0.0692639729216868,
      "mom_capped": false,
      "yoy_capped": false,
      "mom_pct_rank": -0.0483900760405077,
      "yoy_pct_rank": 0.0692639729216868,
      "mom_3m_avg": -0.0417088385722987,
      "vol_12m": 0.0852921675849566,
      "months_seen": 41,
      "mom_pct_rank_z": -0.3615433824892829,
      "yoy_pct_rank_z": -0.0267022072105414,
      "mom_3m_avg_z": -0.4566027558252555,
      "trend_score": -0.2131346695171067,
      "trend_label": "Stable",
      "statefp": "11"
    },
    {
      "date": "2025-06-01",
      "dataset_name": "counties",
      "region_id": "11001",
      "region_name": "District of Columbia, District of Columbia",
      "ntl_sum": 65912.01409244537,
      "area_km2": 176.92983408270678,
      "light_density": 372.5319386307369,
      "density_3m_smooth": 419.8093186796071,
      "lag_1": 459.2239793890578,
      "lag_12": 398.1456134210717,
      "mom_pct_display": -0.0858288383848926,
      "yoy_pct_display": 0.0544115130953967,
      "mom_capped": false,
      "yoy_capped": false,
      "mom_pct_rank": -0.0858288383848926,
      "yoy_pct_rank": 0.0544115130953967,
      "mom_3m_avg": -0.0854013000972186,
      "vol_12m": 0.0864861558886616,
      "months_seen": 42,
      "mom_pct_rank_z": -0.5777267215946165,
      "yoy_pct_rank_z": -0.0836471841647713,
      "mom_3m_avg_z": -0.8265512946036825,
      "trend_score": -0.3804518674815071,
      "trend_label": "Stable",
      "statefp": "11"
    },
    {
      "date": "2025-07-01",
      "dataset_name": "counties",
      "region_id": "11001",
      "region_name": "District of Columbia, District of Columbia",
      "ntl_sum": 66195.5751748085,
      "area_km2": 176.92983408270678,
      "light_density": 374.1346139728195,
      "density_3m_smooth": 389.21423900450674,
      "lag_1": 419.8093186796071,
      "lag_12": 383.4845299441997,
      "mom_pct_display": -0.0728785148727251,
      "yoy_pct_display": 0.0149411739272526,
      "mom_capped": false,
      "yoy_capped": false,
      "mom_pct_rank": -0.0728785148727251,
      "yoy_pct_rank": 0.0149411739272526,
      "mom_3m_avg": -0.0690324764327084,
      "vol_12m": 0.0887687825874522,
      "months_seen": 43,
      "mom_pct_rank_z": -0.502947428582689,
      "yoy_pct_rank_z": -0.2349781812247396,
      "mom_3m_avg_z": -0.6879547911140941,
      "trend_score": -0.4059642774099953,
      "trend_label": "Stable",
      "statefp": "11"
    },
    {
      "date": "2025-08-01",
      "dataset_name": "counties",
      "region_id": "11001",
      "region_name": "District of Columbia, District of Columbia",
      "ntl_sum": 69828.49515008926,
      "area_km2": 176.92983408270678,
      "light_density": 394.6677252715196,
      "density_3m_smooth": 380.444759291692,
      "lag_1": 389.21423900450674,
      "lag_12": 391.1358645607477,
      "mom_pct_display": -0.0225312407255306,
      "yoy_pct_display": -0.027333482397637,
      "mom_capped": false,
      "yoy_capped": false,
      "mom_pct_rank": -0.0225312407255306,
      "yoy_pct_rank": -0.027333482397637,
      "mom_3m_avg": -0.0604128646610494,
      "vol_12m": 0.0889509028224716,
      "months_seen": 44,
      "mom_pct_rank_z": -0.2122262305934991,
      "yoy_pct_rank_z": -0.3970610522322518,
      "mom_3m_avg_z": -0.6149716569882253,
      "trend_score": -0.3851927266918207,
      "trend_label": "Stable",
      "statefp": "11"
    },
    {
      "date": "2025-09-01",
      "dataset_name": "counties",
      "region_id": "11001",
      "region_name": "District of Columbia, District of Columbia",
      "ntl_sum": 65473.58619594574,
      "area_km2": 176.92983408270678,
      "light_density": 370.05396255184286,
      "density_3m_smooth": 379.618767265394,
      "lag_1": 380.444759291692,
      "lag_12": 395.3462709747414,
      "mom_pct_display": -0.0021711221041284,
      "yoy_pct_display": -0.0397815911367285,
      "mom_capped": false,
      "yoy_capped": false,
      "mom_pct_rank": -0.0021711221041284,
      "yoy_pct_rank": -0.0397815911367285,
      "mom_3m_avg": -0.032526959234128,
      "vol_12m": 0.0889019052274587,
      "months_seen": 45,
      "mom_pct_rank_z": -0.0946604203867536,
      "yoy_pct_rank_z": -0.4447876425453644,
      "mom_3m_avg_z": -0.3788588447284017,
      "trend_score": -0.3265637163343886,
      "trend_label": "Stable",
      "statefp": "11"
    },
    {
      "date": "2025-10-01",
      "dataset_name": "counties",
      "region_id": "11001",
      "region_name": "District of Columbia, District of Columbia",
      "ntl_sum": 71510.06269550323,
      "area_km2": 176.92983408270678,
      "light_density": 404.171874496166,
      "density_3m_smooth": 389.6311874398428,
      "lag_1": 379.618767265394,
      "lag_12": 389.6390430036311,
      "mom_pct_display": 0.0263749346392273,
      "yoy_pct_display": -2.01611309990111e-05,
      "mom_capped": false,
      "yoy_capped": false,
      "mom_pct_rank": 0.0263749346392273,
      "yoy_pct_rank": -2.01611309990111e-05,
      "mom_3m_avg": 0.0005575239365227,
      "vol_12m": 0.0890776935087798,
      "months_seen": 46,
      "mom_pct_rank_z": 0.0701736039942513,
      "yoy_pct_rank_z": -0.2923405905536367,
      "mom_3m_avg_z": -0.0987291432182009,
      "trend_score": -0.1448640427221831,
      "trend_label": "Stable",
      "statefp": "11"
    },
    {
      "date": "2025-11-01",
      "dataset_name": "counties",
      "region_id": "11001",
      "region_name": "District of Columbia, District of Columbia",
      "ntl_sum": 78355.51681804657,
      "area_km2": 176.92983408270678,
      "light_density": 442.8620940288616,
      "density_3m_smooth": 405.6959770256235,
      "lag_1": 389.6311874398428,
      "lag_12": 400.0354256643864,
      "mom_pct_display": 0.0412307589937498,
      "yoy_pct_display": 0.0141501252091261,
      "mom_capped": false,
      "yoy_capped": false,
      "mom_pct_rank": 0.0412307589937498,
      "yoy_pct_rank": 0.0141501252091261,
      "mom_3m_avg": 0.0218115238429495,
      "vol_12m": 0.0895204936106517,
      "months_seen": 47,
      "mom_pct_rank_z": 0.1559558658270781,
      "yoy_pct_rank_z": -0.2380110964152356,
      "mom_3m_avg_z": 0.0812306469642508,
      "trend_score": -0.0559726590666442,
      "trend_label": "Stable",
      "statefp": "11"
    },
    {
      "date": "2025-12-01",
      "dataset_name": "counties",
      "region_id": "11001",
      "region_name": "District of Columbia, District of Columbia",
      "ntl_sum": 72024.27918434143,
      "area_km2": 176.92983408270678,
      "light_density": 407.0782045196137,
      "density_3m_smooth": 418.0373910148804,
      "lag_1": 405.6959770256235,
      "lag_12": 407.8669116806972,
      "mom_pct_display": 0.030420350923217,
      "yoy_pct_display": 0.0249357793998872,
      "mom_capped": false,
      "yoy_capped": false,
      "mom_pct_rank": 0.030420350923217,
      "yoy_pct_rank": 0.0249357793998872,
      "mom_3m_avg": 0.032675348185398,
      "vol_12m": 0.0897391475198183,
      "months_seen": 48,
      "mom_pct_rank_z": 0.0935331262001221,
      "yoy_pct_rank_z": -0.1966584291458035,
      "mom_3m_avg_z": 0.1732157583716745,
      "trend_score": -0.0356261250385302,
      "trend_label": "Stable",
      "statefp": "11"
    },
    {
      "date": "2026-01-01",
      "dataset_name": "counties",
      "region_id": "11001",
      "region_name": "District of Columbia, District of Columbia",
      "ntl_sum": 85586.47560930252,
      "area_km2": 176.92983408270678,
      "light_density": 483.731169777137,
      "density_3m_smooth": 444.5571561085374,
      "lag_1": 418.0373910148804,
      "lag_12": 499.4130064115072,
      "mom_pct_display": 0.0634387393655728,
      "yoy_pct_display": -0.1098406521230438,
      "mom_capped": false,
      "yoy_capped": false,
      "mom_pct_rank": 0.0634387393655728,
      "yoy_pct_rank": -0.1098406521230438,
      "mom_3m_avg": 0.0450299497608465,
      "vol_12m": 0.0616910374449665,
      "months_seen": 49,
      "mom_pct_rank_z": 0.2841918183781768,
      "yoy_pct_rank_z": -0.7133971294560071,
      "mom_3m_avg_z": 0.2778234330255734,
      "trend_score": -0.2158763326094358,
      "trend_label": "Stable",
      "statefp": "11"
    }
  ]
}